alhambra_mixes/__init__.py
alhambra_mixes-0.7.0.dist-info/METADATA
alhambra_mixes-0.7.0.dist-info/WHEEL
alhambra_mixes-0.7.0.dist-info/RECORD
